paparse/__init__.py
paparse/configs.py
paparse/converters_primitive.py
paparse/exceptions.py
paparse/parameters.py
paparse/predicates.py
paparse-0.1.0a1.dist-info/METADATA
paparse-0.1.0a1.dist-info/WHEEL
paparse-0.1.0a1.dist-info/top_level.txt
paparse-0.1.0a1.dist-info/RECORD
