Metadata-Version: 2.1
Name: paparse
Version: 0.1.0a1
Summary: Python utility for creating configs from settings files
Home-page: https://github.com/wulu473/paparse
Author: Lukas Wutschitz
License: UNKNOWN
Platform: UNKNOWN
Requires-Python: >=3.9.0
Requires-Dist: multimethod
Requires-Dist: seval
Requires-Dist: pyyaml
